CHANGELOG.md
LICENSE.md
MoleculaPy/__init__.py
MoleculaPy/cli.py
MoleculaPy/data/smiles_desc_output.csv
MoleculaPy/data/smiles_fing_atom_1024_output.csv
MoleculaPy/data/smiles_sample.csv
MoleculaPy/helpers.py
MoleculaPy/moleculapy.py
MoleculaPy/molecule_utils.py
moleculapy-1.1.3.dist-info/entry_points.txt
moleculapy-1.1.3.dist-info/LICENSE.md
moleculapy-1.1.3.dist-info/METADATA
moleculapy-1.1.3.dist-info/WHEEL
moleculapy-1.1.3.dist-info/RECORD
