Metadata-Version: 2.1
Name: MoleculaPy
Version: 1.1.3
Summary: A command-line application that utilizes the RDKit library to compute molecular descriptors and fingerprints, aiding in the analysis and characterization of chemical structures
Home-page: https://github.com/kamilpytlak/MoleculaPy
License: MIT
Keywords: cli,fingerprints,rdkit,chemoinformatics,qsar,molecular-descriptors
Author: Kamil Pytlak
Requires-Python: >=3.9,<4.0
Classifier: License :: OSI Approved :: MIT License
Classifier: Programming Language :: Python :: 3
Classifier: Programming Language :: Python :: 3.9
Classifier: Programming Language :: Python :: 3.10
Classifier: Programming Language :: Python :: 3.11
Requires-Dist: pandas (>=2.2.2,<3.0.0)
Requires-Dist: rdkit (>=2024.3.5,<2025.0.0)
Requires-Dist: tqdm (>=4.66.4,<5.0.0)
Project-URL: Repository, https://github.com/kamilpytlak/MoleculaPy
